{
  "pools": [
    {
      "id": "epoch_pool",
      "path": "gameplay/kreative-generatoren.md#epochen-generator",
      "title": "Random-Epochen-Generator: Wann und wo?"
    },
    {
      "id": "npc_pool",
      "path": "gameplay/kreative-generatoren.md#nsc-generator",
      "title": "NSC-Generator: Begegnungen im Zeitstrom"
    },
    {
      "id": "encounter_pool",
      "path": "gameplay/kreative-generatoren.md#encounter-pool-listen",
      "title": "Encounter-Pool: Schnelle Gegnerlisten nach Risiko"
    },
    {
      "id": "twist_pool",
      "path": "gameplay/kreative-generatoren.md#twist-seeds",
      "title": "Twist-Seeds: Dramatische Wendungen"
    },
    {
      "id": "mission_pool",
      "path": "gameplay/kreative-generatoren.md#missions-generator",
      "title": "Missions-Generator: Kleine Aufträge und Dilemmata"
    },
    {
      "id": "arc_pool",
      "path": "gameplay/kreative-generatoren.md#arc-generator",
      "title": "Arc-Generator: Große Missionen"
    },
    {
      "id": "creature_pool",
      "path": "gameplay/kreative-generatoren.md#kreaturen-generator",
      "title": "Kreaturen- & Gestalten-Generator: Begegnungen der ungewöhnlichen Art"
    },
    {
      "id": "artifact_pool",
      "path": "gameplay/kreative-generatoren.md#artefakt-generator",
      "title": "Artefakt-Generator: Objekte mit Geschichte"
    },
    {
      "id": "culture_pool",
      "path": "gameplay/kreative-generatoren.md#kulturfragmente",
      "title": "Kulturfragmente-Generator: Farbe für die Epochen"
    },
    {
      "id": "anomaly_pool",
      "path": "gameplay/kreative-generatoren.md#anomalien-generator",
      "title": "Temporale Anomalien-Generator (optional)"
    },
    {
      "id": "paracreature_pool",
      "path": "gameplay/kreative-generatoren.md#para-creature-generator",
      "title": "Para-Creature-Generator: Urban Myth Edition"
    },
    {
      "id": "puzzle_pool",
      "path": "gameplay/raetselbibliothek.md",
      "title": "Rätsel-Pool: Easy & Advanced"
    }
  ]
}
